sob/__init__.py
sob/_datetime.py
sob/_inspect.py
sob/_io.py
sob/_types.py
sob/_utilities.py
sob/abc.py
sob/errors.py
sob/hooks.py
sob/meta.py
sob/model.py
sob/properties.py
sob/py.typed
sob/thesaurus.py
sob/types.py
sob/utilities.py
sob/version.py
sob-2.1.1.dist-info/METADATA
sob-2.1.1.dist-info/WHEEL
sob-2.1.1.dist-info/licenses/LICENSE
sob-2.1.1.dist-info/RECORD
