Metadata-Version: 2.4
Name: sob
Version: 2.1.1
Summary: A type-enforced framework for serializing and deserializing JSON
Project-URL: Documentation, https://sob.enorganic.org
Project-URL: Repository, https://github.com/enorganic/sob
Author-email: david@belais.me
License-Expression: MIT
License-File: LICENSE
Keywords: serial
Requires-Python: ~=3.9
Requires-Dist: iso8601~=2.1
Requires-Dist: typing-extensions
